kancolle/__init__.py
kancolle/cli.py
kancolle/data/__init__.py
kancolle/data/data.py
kancolle/data/ship.json
kancolle/data/shipclass.json
kancolle/data/shiptype.json
kancolle/data/slotitem.json
kancolle/kancolle.py
kancolle/models/__init__.py
kancolle/models/ship.py
kancolle/models/ship_class.py
kancolle/models/ship_type.py
kancolle/models/slot_item.py
kancolle-0.2.2.dist-info/LICENSE
kancolle-0.2.2.dist-info/METADATA
kancolle-0.2.2.dist-info/WHEEL
kancolle-0.2.2.dist-info/entry_points.txt
kancolle-0.2.2.dist-info/RECORD
