Metadata-Version: 2.1
Name: kancolle
Version: 0.2.2
Summary: for KanColle assistant software.
Home-page: https://github.com/andychucs/kancolle
License: MIT
Author: Andy Chu
Author-email: andychu@example.com
Requires-Python: >=3.8,<4.0
Classifier: Development Status :: 2 - Pre-Alpha
Classifier: Intended Audience :: Developers
Classifier: License :: OSI Approved :: MIT License
Classifier: Natural Language :: English
Classifier: Programming Language :: Python :: 3
Classifier: Programming Language :: Python :: 3.8
Classifier: Programming Language :: Python :: 3.9
Classifier: Programming Language :: Python :: 3.10
Classifier: Programming Language :: Python :: 3.11
Classifier: Programming Language :: Python :: 3.12
Provides-Extra: dev
Provides-Extra: doc
Provides-Extra: test
Requires-Dist: black (>=21.5b2,<22.0) ; extra == "test"
Requires-Dist: bump2version (>=1.0.1,<2.0.0) ; extra == "dev"
Requires-Dist: click (==8.0.1)
Requires-Dist: flake8 (>=3.9.2,<4.0.0) ; extra == "test"
Requires-Dist: flake8-docstrings (>=1.6.0,<2.0.0) ; extra == "test"
Requires-Dist: isort (>=5.8.0,<6.0.0) ; extra == "test"
Requires-Dist: jinja2 (>=3.1.2,<4.0.0)
Requires-Dist: markupsafe (>=2.0.1,<3.0.0)
Requires-Dist: mkdocs (>=1.5.3,<2.0.0) ; extra == "doc"
Requires-Dist: mkdocs-autorefs (>=0.5.0,<0.6.0) ; extra == "doc"
Requires-Dist: mkdocs-include-markdown-plugin (>=6.0.4,<7.0.0) ; extra == "doc"
Requires-Dist: mkdocs-material (>=6.2.8,<7.0.0) ; extra == "doc"
Requires-Dist: mkdocs-material-extensions (>=1.3.1,<2.0.0)
Requires-Dist: mkdocstrings (>=0.24.0,<0.25.0) ; extra == "doc"
Requires-Dist: mkdocstrings-python (>=1.7.5,<2.0.0) ; extra == "doc"
Requires-Dist: mkdocstrings-python-legacy (>=0.2.3,<0.3.0) ; extra == "doc"
Requires-Dist: mypy (>=1.7.1,<2.0.0) ; extra == "test"
Requires-Dist: pip (>=23.3.2,<24.0.0) ; extra == "dev"
Requires-Dist: pre-commit (>=2.12.0,<3.0.0) ; extra == "dev"
Requires-Dist: pytest (>=6.2.4,<7.0.0) ; extra == "test"
Requires-Dist: pytest-cov (>=2.12.0,<3.0.0) ; extra == "test"
Requires-Dist: requests (>=2.31.0,<3.0.0)
Requires-Dist: toml (>=0.10.2,<0.11.0) ; extra == "dev"
Requires-Dist: tox (>=3.20.1,<4.0.0) ; extra == "dev"
Requires-Dist: twine (>=3.3.0,<4.0.0) ; extra == "dev"
Requires-Dist: types-requests (>=2.31.0.10,<3.0.0.0)
Requires-Dist: virtualenv (>=20.2.2,<21.0.0) ; extra == "dev"
